src/__init__.py
src/prototypes/__init__.py
src/prototypes/cnv.py
src/prototypes/cnvAnalysis.py
src/prototypes/fusionAnalysis.py
src/prototypes/patient.py
src/prototypes/sample.py
src/prototypes/smallVariant.py
src/prototypes/smallVariantAnalysis.py
transmute_common/__init__.py
transmute_common/factories/__init__.py
transmute_common/factories/biomarker.py
transmute_common/factories/biomarkerAnalysis.py
transmute_common/factories/cnv.py
transmute_common/factories/cnvAnalysis.py
transmute_common/factories/fusion.py
transmute_common/factories/fusionAnalysis.py
transmute_common/factories/ihc.py
transmute_common/factories/ihcAnalysis.py
transmute_common/factories/patient.py
transmute_common/factories/sample.py
transmute_common/factories/smallVariant.py
transmute_common/factories/smallVariantAnalysis.py
transmute_common/factories/sv.py
transmute_common/factories/svAnalysis.py
transmute_common/prototypes/__init__.py
transmute_common/prototypes/cnv.py
transmute_common/prototypes/cnvAnalysis.py
transmute_common/prototypes/fusion.py
transmute_common/prototypes/fusionAnalysis.py
transmute_common/prototypes/patient.py
transmute_common/prototypes/sample.py
transmute_common/prototypes/smallVariant.py
transmute_common/prototypes/smallVariantAnalysis.py
transmute_common-0.0.14.dist-info/LICENSE
transmute_common-0.0.14.dist-info/METADATA
transmute_common-0.0.14.dist-info/WHEEL
transmute_common-0.0.14.dist-info/top_level.txt
transmute_common-0.0.14.dist-info/RECORD
