Metadata-Version: 2.1
Name: transmute-common
Version: 0.0.14
Summary: A package to support ETL creation within Transmute
Home-page: https://github.com/finnor/transmute-common-py
Author: Adrian Flannery
Author-email: aflanry@gmail.com
License: UNKNOWN
Platform: UNKNOWN
Classifier: Programming Language :: Python :: 3
Classifier: License :: OSI Approved :: GNU General Public License v3 (GPLv3)
Classifier: Operating System :: OS Independent
Requires-Python: >=3.8
License-File: LICENSE
